{
  "reikai": {
    "entries": {
      "0000": [
        {
          "def": "<ruby><rb>液体</rb><rt>えきたい</rt></ruby>などが、<ruby><rb>低</rb><rt>ひく</rt></ruby>いほうへ<ruby><rb>動</rb><rt>うご</rt></ruby>く。",
          "hyouki": [
            "流れる"
          ]
        },
        {
          "def": "<ruby><rb>時</rb><rt>とき</rt></ruby>がたつ。",
          "hyouki": [
            "流れる"
          ]
        },
        {
          "def": "うかんで<ruby><rb>行</rb><rt>い</rt></ruby>く。",
          "hyouki": [
            "流れる"
          ]
        },
        {
          "def": "<ruby><rb>広</rb><rt>ひろ</rt></ruby>がって<ruby><rb>行</rb><rt>い</rt></ruby>く。",
          "hyouki": [
            "流れる"
          ]
        },
        {
          "def": "とりやめになる。",
          "hyouki": [
            "流れる"
          ]
        }
      ],
      "0001": [
        {
          "def": "<ruby><rb>温度</rb><rt>おんど</rt></ruby>が<ruby><rb>０度</rb><rt>れいど</rt></ruby>より<ruby><rb>低</rb><rt>ひく</rt></ruby>くなって、<ruby><rb>水</rb><rt>みず</rt></ruby>が<ruby><rb>固</rb><rt>かた</rt></ruby>まったもの。",
          "hyouki": [
            "氷"
          ]
        }
      ],
      "0002": [
        {
          "def": "モーターなどで<ruby><rb>回</rb><rt>まわ</rt></ruby>して<ruby><rb>穴</rb><rt>あな</rt></ruby>をあける<ruby><rb>道具</rb><rt>どうぐ</rt></ruby>。",
          "hyouki": [
            "ドリル"
          ]
        },
        {
          "def": "くり<ruby><rb>返</rb><rt>かえ</rt></ruby>してする<ruby><rb>練習</rb><rt>れんしゅう</rt></ruby>。",
          "hyouki": [
            "ドリル"
          ]
        }
      ],
      "0003": [
        {
          "def": "こわす。くだく。",
          "hyouki": [
            "割る"
          ]
        },
        {
          "def": "<ruby><rb>細</rb><rt>こま</rt></ruby>かくする。<ruby><rb>小</rb><rt>ちい</rt></ruby>さくする。",
          "hyouki": [
            "割る"
          ]
        },
        {
          "def": "<ruby><rb>混</rb><rt>ま</rt></ruby>ぜてうすめる。",
          "hyouki": [
            "割る"
          ]
        },
        {
          "def": "ありのままをかくさずに<ruby><rb>言</rb><rt>い</rt></ruby>う。",
          "hyouki": [
            "割る"
          ]
        },
        {
          "def": "<ruby><rb>外</rb><rt>そと</rt></ruby>に<ruby><rb>出</rb><rt>で</rt></ruby>る。",
          "hyouki": [
            "割る"
          ]
        },
        {
          "def": "ものごとがある<ruby><rb>数量</rb><rt>すうりょう</rt></ruby>より<ruby><rb>下</rb><rt>した</rt></ruby>になる。",
          "hyouki": [
            "割る"
          ]
        },
        {
          "def": "<ruby><rb>割</rb><rt>わ</rt></ruby>り<ruby><rb>算</rb><rt>ざん</rt></ruby>をする。<ruby><rb>記号</rb><rt>きごう</rt></ruby>は「÷」。",
          "hyouki": [
            "割る"
          ]
        }
      ],
      "0004": [
        {
          "def": "<ruby><rb>気象</rb><rt>きしょう</rt></ruby>や<ruby><rb>地震</rb><rt>じしん</rt></ruby>の<ruby><rb>観測</rb><rt>かんそく</rt></ruby>をする<ruby><rb>役所</rb><rt>やくしょ</rt></ruby>。<ruby><rb>天気予報</rb><rt>てんきよほう</rt></ruby>の<ruby><rb>発表</rb><rt>はっぴょう</rt></ruby>もする。",
          "hyouki": [
            "気象台"
          ]
        }
      ]
    }
  }
}
