{
  "cate": "4",
  "date": "1æ19æ¥ 14æ04å",
  "datetime": "2019-01-19T14:04",
  "video": "/news/html/20190119/movie/k10011783691_201901191401_201901191404.html",
  "duration": 41,
  "img": "html/20190119/K10011783691_1901191401_1901191404_01_03.jpg",
  "title": "成人年齢引き下げに関心を 若者対象に動画コンテスト 法務省",
  "summary": "３年後の成人年齢の引き下げに関心を持ってもらおうと、法務省は若者を対象にした動画コンテストを行うことになりました。",
  "more": "成人年齢は去年の民法の改正で３年後の2022年から20歳から18歳に引き下げられることになっていて、成人式に出席する人の年齢など影響が予想されています。<br /><br />これに関連して、さまざまなことを考えるきっかけにしてもらおうと、法務省は若者を対象にした動画コンテストを行うことになりました。<br /><br />成人年齢の引き下げに関係があればテーマは自由で、15秒から90秒の動画を作成して動画投稿サイトのユーチューブに投稿し、その後、法務省の特設サイトにＵＲＬを登録すれば応募できます。<br /><br />応募できるのは29歳以下の人で、募集は来月28日までとなっています。<br /><br />優れた作品には３月に法務大臣賞などが贈られます。<br /><br />法務省は「成人年齢の引き下げが自分にどういう影響があるか考える機会にしてもらえれば」と話しています。",
  "body": [
    {
      "title": "",
      "img": "",
      "align": "",
      "text": "",
      "textPos": ""
    }
  ],
  "relationNews": [
    {
      "link": "html/20190114/k10011777011000.html",
      "title": "若者の７割 成人年齢引き下げ後も20歳での成人式希望",
      "date": "1月14日  7時01分",
      "datetime": "2019-01-14T07:01",
      "imgPath": "html/20190114/K10011777011_1901140655_1901140701_01_02.jpg",
      "iconPath": "html/20190114/K10011777011_1901140655_1901140701_02_01.jpg",
      "video": "",
      "duration": 0
    }
  ],
  "relationLink": [],
  "word": [],
  "news_id": "k10011783691000",
  "yyyy": "2019",
  "mm": "01",
  "dd": "19",
  "url": "https://www3.nhk.or.jp/news/html/20190119/k10011783691000.html?utm_int=news-new_contents_list-items_014"
}